memcom/PROJECT.txt
memcom/__init__.py
memcom/mc_audio.py
memcom/mc_blank.py
memcom/mc_clock.py
memcom/mc_filter.py
memcom/mc_message.py
memcom/mc_record.py
memcom/mc_shapes.py
memcom/mc_testvid.py
memcom/mc_video.py
memcom-0.1.1.dist-info/LICENSE
memcom-0.1.1.dist-info/METADATA
memcom-0.1.1.dist-info/WHEEL
memcom-0.1.1.dist-info/top_level.txt
memcom-0.1.1.dist-info/RECORD
