Metadata-Version: 2.1
Name: memcom
Version: 0.1.1
Summary: Interprocess real time message/audio/video buffers
Home-page: https://github.com/wheresjames/memcom
Author: Robert Umbehant
Author-email: memcom@wheresjames.com
License: MIT
Platform: UNKNOWN
License-File: LICENSE
Requires-Dist: Pillow
Requires-Dist: av
Requires-Dist: propertybag
Requires-Dist: sparen
